symbeam/__init__.py
symbeam/beam.py
symbeam/load.py
symbeam/point.py
symbeam/spring.py
symbeam/utils/__init__.py
symbeam/utils/generate_output_baseline.py
symbeam/utils/utils.py
symbeam-2.1.1.dist-info/licenses/LICENSE.txt
symbeam-2.1.1.dist-info/METADATA
symbeam-2.1.1.dist-info/WHEEL
symbeam-2.1.1.dist-info/top_level.txt
symbeam-2.1.1.dist-info/RECORD
