Metadata-Version: 2.4
Name: symbeam
Version: 2.1.1
Summary: A pedagogical package for bending diagrams
Author-email: "António Manuel Couto Carneiro @FEUP" <amcc@fe.up.pt>
Project-URL: Homepage, https://github.com/amcc1996/symbeam
Project-URL: Download, https://github.com/amcc1996/symbeam/releases/tag/1.1.1
Project-URL: Source, https://github.com/amcc1996/symbeam
Project-URL: Tracker, https://github.com/amcc1996/symbeam/issues
Keywords: bending-moment-diagrams,statics,sympy,python3
Classifier: Development Status :: 4 - Beta
Classifier: Environment :: Console
Classifier: Intended Audience :: Science/Research
Classifier: Intended Audience :: Education
Classifier: License :: OSI Approved :: MIT License
Classifier: Natural Language :: English
Classifier: Programming Language :: Python :: 3.8
Classifier: Programming Language :: Python :: 3.9
Classifier: Programming Language :: Python :: 3.10
Classifier: Programming Language :: Python :: 3.11
Classifier: Programming Language :: Python :: 3.12
Classifier: Programming Language :: Python :: 3.13
Classifier: Topic :: Scientific/Engineering
Classifier: Topic :: Scientific/Engineering :: Physics
Classifier: Topic :: Scientific/Engineering :: Mathematics
Requires-Python: >=3.6
License-File: LICENSE.txt
Requires-Dist: certifi>=2020.6.20
Requires-Dist: cycler>=0.10.0
Requires-Dist: kiwisolver>=1.2.0
Requires-Dist: matplotlib>=3.3.1
Requires-Dist: mpmath>=1.1.0
Requires-Dist: numpy>=1.19.1
Requires-Dist: Pillow>=7.2.0
Requires-Dist: pyparsing>=2.4.7
Requires-Dist: python-dateutil>=2.8.1
Requires-Dist: six>=1.15.0
Requires-Dist: sympy>=1.6.2
Dynamic: license-file
